setup.py
optuna_firestore_proto/__init__.py
optuna_firestore_proto/study_pb2.py
optuna_firestore_proto/study_pb2_grpc.py
optuna_firestore_proto/trial_pb2.py
optuna_firestore_proto/trial_pb2_grpc.py
optuna_firestore_storage/__init__.py
optuna_firestore_storage/rpc_storage.py
optuna_firestore_storage/version.py
optuna_firestore_storage.egg-info/PKG-INFO
optuna_firestore_storage.egg-info/SOURCES.txt
optuna_firestore_storage.egg-info/dependency_links.txt
optuna_firestore_storage.egg-info/requires.txt
optuna_firestore_storage.egg-info/top_level.txt